minihai/__init__.py
minihai/__main__.py
minihai/art.py
minihai/conf.py
minihai/consts.py
minihai/app/__init__.py
minihai/app/auth.py
minihai/app/schema.py
minihai/app/utils.py
minihai/app/routers/__init__.py
minihai/app/routers/commits.py
minihai/app/routers/data.py
minihai/app/routers/executions.py
minihai/app/routers/misc.py
minihai/app/routers/public.py
minihai/cli/__init__.py
minihai/lib/__init__.py
minihai/lib/cache.py
minihai/lib/events.py
minihai/models/__init__.py
minihai/models/base.py
minihai/models/commit.py
minihai/models/execution.py
minihai/models/output.py
minihai/services/__init__.py
minihai/services/docker.py
minihai/services/execution.py
minihai-0.1.dist-info/METADATA
minihai-0.1.dist-info/WHEEL
minihai-0.1.dist-info/entry_points.txt
minihai-0.1.dist-info/top_level.txt
minihai-0.1.dist-info/RECORD
