Metadata-Version: 2.1
Name: minihai
Version: 0.1
Summary: A small shark
Home-page: UNKNOWN
Author: Valohai
Author-email: hait@valohai.com
License: UNKNOWN
Platform: UNKNOWN
Requires-Dist: aiofiles (==0.5.0)
Requires-Dist: attrs (==19.3.0)
Requires-Dist: certifi (==2020.4.5.1)
Requires-Dist: cffi (==1.14.0)
Requires-Dist: chardet (==3.0.4)
Requires-Dist: click (==7.1.2)
Requires-Dist: cryptography (==2.9.2)
Requires-Dist: docker (==4.2.0)
Requires-Dist: fastapi (==0.54.1)
Requires-Dist: h11 (==0.9.0)
Requires-Dist: httptools (==0.1.1)
Requires-Dist: idna (==2.9)
Requires-Dist: importlib-metadata (==1.6.0)
Requires-Dist: jsonschema (==3.2.0)
Requires-Dist: pycparser (==2.20)
Requires-Dist: pydantic (==1.5.1)
Requires-Dist: pyjwt (==1.7.1)
Requires-Dist: pyopenssl (==19.1.0)
Requires-Dist: pyrsistent (==0.16.0)
Requires-Dist: python-multipart (==0.0.5)
Requires-Dist: pyyaml (==5.3.1)
Requires-Dist: requests-toolbelt (==0.9.1)
Requires-Dist: requests[security] (==2.23.0)
Requires-Dist: six (==1.14.0)
Requires-Dist: starlette (==0.13.2)
Requires-Dist: ulid2 (==0.2.0)
Requires-Dist: urllib3 (==1.25.9)
Requires-Dist: uvicorn (==0.11.5)
Requires-Dist: uvloop (==0.14.0)
Requires-Dist: valohai-cli (==0.12.1)
Requires-Dist: valohai-yaml (==0.10.0)
Requires-Dist: websocket-client (==0.57.0)
Requires-Dist: websockets (==8.1)
Requires-Dist: zipp (==3.1.0)
